convertspeechtotext_STT/__init__.py
convertspeechtotext-0.0.1.dist-info/METADATA
convertspeechtotext-0.0.1.dist-info/WHEEL
convertspeechtotext-0.0.1.dist-info/top_level.txt
convertspeechtotext-0.0.1.dist-info/RECORD
